WhoIAm.py
whoiam-1.0.0.dist-info/WHEEL
whoiam-1.0.0.dist-info/METADATA
whoiam-1.0.0.dist-info/RECORD
