Metadata-Version: 2.1
Name: whoiam
Version: 1.0.0
Summary: WhoIAm()
Author: None
Requires-Python: >=3.8,<4.0
Classifier: Programming Language :: Python :: 3
Classifier: Programming Language :: Python :: 3.8
Classifier: Programming Language :: Python :: 3.9
